{"skeleton":{"hash":"wVsPTR251zHel6mxt7jcmzqJIvk","spine":"3.8.99","x":-630.26,"y":-710.13,"width":2234.21,"height":1415.61,"images":"","audio":"F:/工作文件/赛车/匹配1/VS"},"bones":[{"name":"root"},{"name":"all","parent":"root","scaleX":1.1181,"scaleY":1.1181,"color":"17ff00ff"},{"name":"lan","parent":"all","x":-580.56,"y":457.51,"color":"00ccffff"},{"name":"lanche","parent":"lan","x":651.87,"y":-18.87,"scaleX":-0.7468,"scaleY":0.7468},{"name":"zi","parent":"all","x":564.57,"y":-441.4,"color":"ff00f9ff"},{"name":"hongche","parent":"zi","x":-651.77,"y":2.13,"scaleX":0.7209,"scaleY":0.7209},{"name":"fense","parent":"zi","x":-3.16,"y":0.04},{"name":"lanse","parent":"lan","x":15.99,"y":-0.23},{"name":"eff","parent":"all","color":"cad5c9ff"},{"name":"vs","parent":"eff"},{"name":"v","parent":"vs","x":-112.66,"y":-3.74},{"name":"s","parent":"vs","x":140.69,"y":82.49},{"name":"name_02","parent":"zi","x":-226.14,"y":-6.85},{"name":"name_01","parent":"lan","x":247.17,"y":-7.01},{"name":"shandianxiao","parent":"eff"},{"name":"xishandian1","parent":"eff"},{"name":"eff/images/glow_0022","parent":"eff","x":1307.2,"y":-89.43},{"name":"eff/images/glow_22","parent":"eff","x":1307.2,"y":-89.43},{"name":"eff/images/glow_23","parent":"eff","x":1307.2,"y":-89.43},{"name":"mohu_00000","parent":"eff","color":"666660ff"},{"name":"mohu_0","parent":"eff","color":"666660ff"},{"name":"ssanshe2","parent":"eff","color":"949c94ff"},{"name":"xishandian2","parent":"all","x":-80.17,"y":469.16},{"name":"eff/images/xxshandian_01","parent":"eff","color":"b3c6b1ff"},{"name":"maskhei_00000","parent":"all","x":1069.49,"y":402.39,"color":"b3c6b1ff"}],"slots":[{"name":"maskhei_00000","bone":"maskhei_00000","attachment":"maskhei_00000"},{"name":"fense","bone":"fense","attachment":"fense"},{"name":"lanse","bone":"lanse","attachment":"lanse"},{"name":"s","bone":"s","attachment":"s"},{"name":"v","bone":"v","attachment":"v"},{"name":"lanche","bone":"lanche","attachment":"lanche"},{"name":"hongche","bone":"hongche","attachment":"hongche"},{"name":"name_01","bone":"name_01"},{"name":"name_02","bone":"name_02"},{"name":"eff/images/xinshandian_01","bone":"shandianxiao","attachment":"eff/images/xinshandian_01","blend":"additive"},{"name":"eff/images/xishandian_01","bone":"xishandian1","attachment":"eff/images/xishandian_01","blend":"additive"},{"name":"eff/images/xishandian_1","bone":"xishandian2","attachment":"eff/images/xishandian_01","blend":"additive"},{"name":"eff/images/glow_0022","bone":"eff/images/glow_0022","attachment":"eff/images/glow_0022","blend":"additive"},{"name":"eff/images/glow_23","bone":"eff/images/glow_23","attachment":"eff/images/glow_0022","blend":"additive"},{"name":"eff/images/glow_22","bone":"eff/images/glow_22","attachment":"eff/images/glow_0022","blend":"additive"},{"name":"mohu_00000","bone":"mohu_00000","attachment":"mohu_00000"},{"name":"mohu_0","bone":"mohu_0","attachment":"mohu_00000","blend":"additive"},{"name":"ssanshe2","bone":"ssanshe2","attachment":"ssanshe2","blend":"additive"},{"name":"eff/images/xxshandian_01","bone":"eff/images/xxshandian_01","attachment":"eff/images/xxshandian_01","blend":"additive"}],"skins":[{"name":"default","attachments":{"eff/images/glow_0022":{"eff/images/glow_0022":{"x":-0.65,"y":0.45,"width":256,"height":256}},"eff/images/glow_22":{"eff/images/glow_0022":{"x":-0.65,"y":0.45,"width":256,"height":256}},"eff/images/glow_23":{"eff/images/glow_0022":{"x":-0.65,"y":0.45,"width":256,"height":256}},"eff/images/xinshandian_01":{"eff/images/xinshandian_01":{"width":128,"height":128},"eff/images/xinshandian_02":{"width":128,"height":128},"eff/images/xinshandian_03":{"width":128,"height":128},"eff/images/xinshandian_04":{"width":128,"height":128},"eff/images/xinshandian_05":{"width":128,"height":128},"eff/images/xinshandian_06":{"width":128,"height":128},"eff/images/xinshandian_07":{"width":128,"height":128},"eff/images/xinshandian_08":{"width":128,"height":128}},"eff/images/xishandian_01":{"eff/images/xishandian_01":{"width":512,"height":128},"eff/images/xishandian_02":{"width":512,"height":128},"eff/images/xishandian_03":{"width":512,"height":128},"eff/images/xishandian_04":{"width":512,"height":128}},"eff/images/xishandian_1":{"eff/images/xishandian_01":{"width":512,"height":128},"eff/images/xishandian_02":{"width":512,"height":128},"eff/images/xishandian_03":{"width":512,"height":128},"eff/images/xishandian_04":{"width":512,"height":128}},"eff/images/xxshandian_01":{"eff/images/xxshandian_01":{"width":128,"height":128},"eff/images/xxshandian_02":{"width":128,"height":128},"eff/images/xxshandian_03":{"width":128,"height":128},"eff/images/xxshandian_04":{"width":128,"height":128},"eff/images/xxshandian_05":{"width":128,"height":128},"eff/images/xxshandian_06":{"width":128,"height":128},"eff/images/xxshandian_07":{"width":128,"height":128},"eff/images/xxshandian_08":{"width":128,"height":128},"eff/images/xxshandian_09":{"width":128,"height":128},"eff/images/xxshandian_10":{"width":128,"height":128},"eff/images/xxshandian_11":{"width":128,"height":128},"eff/images/xxshandian_12":{"width":128,"height":128},"eff/images/xxshandian_13":{"width":128,"height":128},"eff/images/xxshandian_14":{"width":128,"height":128},"eff/images/xxshandian_15":{"width":128,"height":128},"eff/images/xxshandian_16":{"width":128,"height":128}},"fense":{"fense":{"x":-489.91,"y":-6.44,"width":981,"height":240}},"hongche":{"hongche":{"x":-20.09,"y":-16.18,"width":729,"height":511}},"lanche":{"lanche":{"x":-22.71,"y":11.03,"width":729,"height":493}},"lanse":{"lanse":{"x":491.38,"y":-3.09,"width":981,"height":240}},"maskhei_00000":{"maskhei_00000":{"x":3.95,"y":3.95,"width":128,"height":128}},"mohu_0":{"mohu_00000":{"x":-5.82,"y":-15.98,"width":256,"height":512}},"mohu_00000":{"mohu_00000":{"x":-5.82,"y":-15.98,"width":256,"height":512}},"name_01":{"mingzi":{"x":-0.67,"y":0.65,"width":303,"height":73}},"name_02":{"mingzi":{"width":303,"height":73}},"s":{"s":{"x":-5.69,"y":101.97,"width":293,"height":593}},"ssanshe2":{"ssanshe2":{"rotation":180,"width":256,"height":256}},"v":{"v":{"x":31.94,"y":-119.5,"width":279,"height":612}}}}],"animations":{"Effect_VS":{"slots":{"eff/images/glow_0022":{"color":[{"color":"1bdae500"},{"time":0.2333,"color":"1bdae5ff"},{"time":0.4667,"color":"1bdae500"}]},"eff/images/glow_22":{"color":[{"color":"dc4fff00"},{"time":0.2333,"color":"dd4fffff"},{"time":0.4667,"color":"dc4fff00"}]},"eff/images/glow_23":{"color":[{"color":"fc9e0f00","curve":"stepped"},{"time":0.3333,"color":"fc9e0f00"},{"time":0.4667,"color":"fc9e0fff"},{"time":0.6333,"color":"fc9e0f00"}]},"eff/images/xinshandian_01":{"attachment":[{"name":null},{"time":0.4,"name":"eff/images/xinshandian_01"},{"time":0.4333,"name":"eff/images/xinshandian_02"},{"time":0.4667,"name":"eff/images/xinshandian_03"},{"time":0.5,"name":"eff/images/xinshandian_04"},{"time":0.5333,"name":"eff/images/xinshandian_05"},{"time":0.5667,"name":"eff/images/xinshandian_06"},{"time":0.6,"name":"eff/images/xinshandian_07"},{"time":0.6333,"name":"eff/images/xinshandian_08"},{"time":0.6667,"name":null}]},"eff/images/xishandian_01":{"color":[{"time":0.3333,"color":"ffffffff"},{"time":0.4333,"color":"ffffff00"}],"attachment":[{"name":null},{"time":0.1667,"name":"eff/images/xishandian_01"},{"time":0.2333,"name":"eff/images/xishandian_02"},{"time":0.3333,"name":"eff/images/xishandian_03"},{"time":0.4333,"name":"eff/images/xishandian_04"}]},"eff/images/xishandian_1":{"color":[{"time":0.3333,"color":"ffffffff"},{"time":0.4333,"color":"ffffff00"}],"attachment":[{"name":null},{"time":0.1667,"name":"eff/images/xishandian_01"},{"time":0.2333,"name":"eff/images/xishandian_02"},{"time":0.3333,"name":"eff/images/xishandian_03"},{"time":0.4333,"name":"eff/images/xishandian_04"}]},"eff/images/xxshandian_01":{"attachment":[{"name":null},{"time":0.3,"name":"eff/images/xxshandian_01"},{"time":0.3333,"name":"eff/images/xxshandian_02"},{"time":0.3667,"name":"eff/images/xxshandian_03"},{"time":0.4,"name":"eff/images/xxshandian_04"},{"time":0.4333,"name":"eff/images/xxshandian_05"},{"time":0.4667,"name":"eff/images/xxshandian_06"},{"time":0.5,"name":"eff/images/xxshandian_07"},{"time":0.5333,"name":"eff/images/xxshandian_08"},{"time":0.5667,"name":"eff/images/xxshandian_09"},{"time":0.6,"name":"eff/images/xxshandian_10"},{"time":0.6333,"name":"eff/images/xxshandian_11"},{"time":0.6667,"name":"eff/images/xxshandian_12"},{"time":0.7,"name":"eff/images/xxshandian_13"},{"time":0.7333,"name":"eff/images/xxshandian_14"},{"time":0.7667,"name":"eff/images/xxshandian_15"},{"time":0.8,"name":"eff/images/xxshandian_16"},{"time":0.8333,"name":null}]},"fense":{"color":[{"time":1,"color":"ffffffff"},{"time":1.1667,"color":"ffffff00"}]},"hongche":{"color":[{"time":1,"color":"ffffffff"},{"time":1.1667,"color":"ffffff00"}]},"lanche":{"color":[{"time":1,"color":"ffffffff"},{"time":1.1667,"color":"ffffff00"}]},"lanse":{"color":[{"time":1,"color":"ffffffff"},{"time":1.1667,"color":"ffffff00"}]},"maskhei_00000":{"color":[{"color":"ffffff00"},{"time":0.3,"color":"ffffffb0","curve":"stepped"},{"time":0.5333,"color":"ffffffb0"},{"time":1.1667,"color":"ffffff00"}]},"mohu_0":{"color":[{"color":"ffffff00","curve":"stepped"},{"time":0.2667,"color":"ffffff00","curve":0,"c2":0.25,"c3":0.75},{"time":0.3667,"color":"ffffffff"},{"time":0.4667,"color":"ffffff00"}]},"mohu_00000":{"color":[{"color":"ffffff00","curve":"stepped"},{"time":0.2667,"color":"ffffff00","curve":0,"c2":0.25,"c3":0.75},{"time":0.3667,"color":"ffffffff"},{"time":0.4333,"color":"ffffff00"}]},"s":{"color":[{"color":"ffffff00","curve":"stepped"},{"time":0.2,"color":"ffffff00"},{"time":0.2667,"color":"ffffff7f"},{"time":0.6667,"color":"ffffffff","curve":"stepped"},{"time":1,"color":"ffffffff"},{"time":1.1667,"color":"ffffff00"}]},"ssanshe2":{"color":[{"color":"ffffff00","curve":"stepped"},{"time":0.3,"color":"ffffff00"},{"time":0.4,"color":"ffffffff"},{"time":0.5333,"color":"ffffff00"}]},"v":{"color":[{"color":"ffffff00","curve":"stepped"},{"time":0.2,"color":"ffffff00"},{"time":0.2667,"color":"ffffff7f"},{"time":0.6667,"color":"ffffffff","curve":"stepped"},{"time":1,"color":"ffffffff"},{"time":1.1667,"color":"ffffff00"}]}},"bones":{"zi":{"translate":[{"x":460.53},{"time":0.1333,"x":0.35}]},"lan":{"translate":[{"x":-420.76},{"time":0.1,"x":1.87}]},"vs":{"scale":[{"x":4,"y":4,"curve":0.162,"c2":0.57,"c3":0.75},{"time":0.2667,"x":3.915,"y":3.915,"curve":0.162,"c2":0.57,"c3":0.75},{"time":0.4667}]},"shandianxiao":{"scale":[{"x":3,"y":3}]},"fense":{"scale":[{"x":0.5,"curve":"stepped"},{"time":0.1,"x":0.5,"curve":0,"c2":0.53,"c3":0.75},{"time":0.2,"x":1.6},{"time":0.3}]},"lanse":{"scale":[{"x":0.5,"curve":"stepped"},{"time":0.1,"x":0.5,"curve":0.019,"c2":0.51,"c3":0.75},{"time":0.2,"x":1.6},{"time":0.3}]},"xishandian1":{"translate":[{"x":84.81,"y":-444.15}],"scale":[{"x":-2.7,"y":1.685}]},"eff/images/glow_0022":{"translate":[{"x":-1276.19,"y":523.26}],"scale":[{"x":3.022,"y":0.562,"curve":0,"c2":0.61,"c3":0.75},{"time":0.2333,"x":9.82,"y":3.233}]},"eff/images/glow_22":{"translate":[{"x":-1276.19,"y":-317.55}],"scale":[{"x":3.022,"y":0.562,"curve":0,"c2":0.61,"c3":0.75},{"time":0.2333,"x":9.82,"y":3.233}]},"eff/images/glow_23":{"translate":[{"x":-1307.2,"y":89.43}],"scale":[{"x":3.022,"y":0.562,"curve":0,"c2":0.61,"c3":0.75},{"time":0.3333,"x":0,"y":0,"curve":0,"c2":0.61,"c3":0.75},{"time":0.4667,"x":10,"y":10},{"time":0.6333,"x":20,"y":20}]},"mohu_00000":{"scale":[{"x":1.699,"y":1.699,"curve":"stepped"},{"time":0.2667,"x":1.699,"y":1.699,"curve":0,"c2":0.25,"c3":0.75},{"time":0.4333,"x":8.746,"y":8.746}]},"mohu_0":{"scale":[{"x":1.699,"y":1.699,"curve":"stepped"},{"time":0.2667,"x":1.699,"y":1.699,"curve":0,"c2":0.25,"c3":0.75},{"time":0.4667,"x":8.746,"y":8.746}]},"ssanshe2":{"scale":[{"time":0.3},{"time":0.3667,"x":1.515,"y":1.515},{"time":0.5333,"x":8.485,"y":8.485}]},"xishandian2":{"translate":[{"x":-146.8,"y":14.61}],"scale":[{"x":-2.7,"y":1.685}]},"eff/images/xxshandian_01":{"translate":[{"x":44.93,"y":53.21}],"scale":[{"x":2.917,"y":2.917}]},"maskhei_00000":{"translate":[{"x":-1069.49,"y":-402.39}],"scale":[{"x":11.061,"y":18.246}]}}}}}